{"v":"5.1.0","fr":25,"ip":0,"op":42,"w":186,"h":126,"nm":"04-我的-裁切-合","ddd":1,"assets":[],"layers":[{"ddd":0,"ind":1,"ty":3,"nm":"Blue Solid 1","sr":1,"ks":{"o":{"a":0,"k":100,"ix":11},"r":{"a":0,"k":0,"ix":10},"p":{"a":0,"k":[93,88.5,0],"ix":2},"a":{"a":0,"k":[93,88.5,0],"ix":1},"s":{"a":0,"k":[100,100,100],"ix":6}},"ao":0,"ip":0,"op":42,"st":0,"bm":0},{"ddd":0,"ind":2,"ty":4,"nm":"我的-选中态","parent":1,"sr":1,"ks":{"o":{"a":1,"k":[{"i":{"x":[0.833],"y":[1]},"o":{"x":[0.167],"y":[0]},"n":["0p833_1_0p167_0"],"t":1,"s":[0],"e":[100]},{"i":{"x":[0.833],"y":[1]},"o":{"x":[0.167],"y":[0]},"n":["0p833_1_0p167_0"],"t":6,"s":[100],"e":[100]},{"i":{"x":[0.667],"y":[1]},"o":{"x":[0.333],"y":[0]},"n":["0p667_1_0p333_0"],"t":36,"s":[100],"e":[0]},{"t":41}],"ix":11},"r":{"a":0,"k":0,"ix":10},"p":{"a":0,"k":[92.967,111.058,0],"ix":2},"a":{"a":0,"k":[0,0,0],"ix":1},"s":{"a":0,"k":[100,100,100],"ix":6}},"ao":0,"shapes":[{"ty":"gr","it":[{"ind":0,"ty":"sh","ix":1,"ks":{"a":0,"k":{"i":[[0,0],[1.32,-0.35],[0,0],[0,0],[-0.31,-1.19],[-0.26,-0.73],[2.07,-0.75],[0,0],[-1.52,1.28],[-0.41,-0.53],[-0.94,0],[-0.55,3.12],[0,0],[0,0],[0.25,0],[0.66,0.99],[0.26,0.59],[-0.99,2.03],[0,0],[0.95,-1.14],[0.09,0.42],[0.13,1.45],[0,0],[0,0],[0,0],[0,2.16],[0,0],[-0.13,-1.72],[0,0],[0,0],[-0.95,0.33],[0,0],[3.08,-0.33],[0,0],[-1.1,0.22],[0,0],[0,0],[0,0],[0,0],[0,0],[1.52,-0.24],[0,0],[-1.32,0.28],[0,0],[0.55,0],[0.77,0.09],[0,0],[0,0],[0,1.41],[0,0],[-1.19,0.4]],"o":[[-1.19,0.4],[0,0],[0,0],[0.17,1.6],[0.2,0.79],[-1.54,1.4],[0,0],[1.89,-0.72],[0.33,0.7],[1.04,1.29],[1.06,0],[0,0],[0,0],[-0.25,1.77],[-0.35,0],[-0.26,-0.39],[1.36,-1.45],[0,0],[-0.71,1.45],[-0.11,-0.35],[-0.26,-0.97],[0,0],[0,0],[0,0],[-0.13,-1.63],[0,0],[0,2.07],[0,0],[0,0],[1.03,-0.28],[0,0],[-2.37,0.97],[0,0],[1.16,-0.18],[0,0],[0,0],[0,0],[0,0],[0,0],[-1.39,0.28],[0,0],[1.4,-0.22],[0,0],[0,0.53],[-0.7,0],[0,0],[0,0],[1.47,0],[0,0],[1.32,-0.35],[0,0]],"v":[[-10.483,0.055],[-14.243,1.175],[-14.243,-2.275],[-9.313,-2.275],[-8.593,1.925],[-7.913,4.195],[-13.323,7.425],[-12.153,9.225],[-7.053,6.215],[-5.933,8.045],[-2.963,9.995],[-0.543,5.295],[-2.383,4.325],[-2.493,5.095],[-3.243,7.755],[-4.763,6.255],[-5.533,4.765],[-2.013,-0.455],[-3.813,-1.395],[-6.303,2.495],[-6.613,1.355],[-7.203,-2.275],[-0.733,-2.275],[-0.733,-4.275],[-7.383,-4.275],[-7.583,-9.955],[-9.693,-9.955],[-9.493,-4.275],[-14.243,-4.275],[-14.243,-7.075],[-11.273,-7.995],[-12.003,-9.955],[-20.183,-8.015],[-19.743,-6.035],[-16.353,-6.615],[-16.353,-4.275],[-20.713,-4.275],[-20.713,-2.275],[-16.353,-2.275],[-16.353,1.665],[-20.713,2.455],[-20.423,4.545],[-16.353,3.775],[-16.353,7.355],[-17.193,8.155],[-19.393,8.015],[-18.933,10.025],[-16.463,10.025],[-14.243,7.885],[-14.243,3.285],[-10.483,2.185]],"c":true},"ix":2},"nm":"Path 1","mn":"ADBE Vector Shape - Group","hd":false},{"ind":1,"ty":"sh","ix":2,"ks":{"a":0,"k":{"i":[[1.56,0.99],[0,0],[-0.92,-0.97],[0,0]],"o":[[0,0],[1.67,1.12],[0,0],[-1.1,-0.99]],"v":[[-5.157,-9.757],[-6.567,-8.417],[-2.697,-5.287],[-1.177,-6.787]],"c":true},"ix":2},"nm":"Path 2","mn":"ADBE Vector Shape - Group","hd":false},{"ind":2,"ty":"sh","ix":3,"ks":{"a":0,"k":{"i":[[0,0],[0,0],[-0.22,1.21],[0,0],[0.4,-1.18],[0,0],[0,0],[0,0],[0,0],[0,0],[0,0],[0,0]],"o":[[0,0],[0.42,-1.05],[0,0],[-0.18,1.28],[0,0],[0,0],[0,0],[0,0],[0,0],[0,0],[0,0],[0,0]],"v":[[9.361,-6.373],[5.971,-6.373],[6.941,-9.753],[4.851,-10.043],[3.971,-6.373],[1.881,-6.373],[1.881,9.577],[3.881,9.577],[3.881,7.797],[7.361,7.797],[7.361,8.947],[9.361,8.947]],"c":true},"ix":2},"nm":"Path 3","mn":"ADBE Vector Shape - Group","hd":false},{"ind":3,"ty":"sh","ix":4,"ks":{"a":0,"k":{"i":[[0,0],[0,0],[0,0],[0,0]],"o":[[0,0],[0,0],[0,0],[0,0]],"v":[[3.883,5.859],[3.883,1.529],[7.363,1.529],[7.363,5.859]],"c":true},"ix":2},"nm":"Path 4","mn":"ADBE Vector Shape - Group","hd":false},{"ind":4,"ty":"sh","ix":5,"ks":{"a":0,"k":{"i":[[0,0],[0,0],[0,0],[0,0]],"o":[[0,0],[0,0],[0,0],[0,0]],"v":[[3.883,-0.339],[3.883,-4.389],[7.363,-4.389],[7.363,-0.339]],"c":true},"ix":2},"nm":"Path 5","mn":"ADBE Vector Shape - Group","hd":false},{"ind":5,"ty":"sh","ix":6,"ks":{"a":0,"k":{"i":[[1.46,1.8],[0,0],[-0.84,-1.46],[0,0]],"o":[[0,0],[1.41,1.78],[0,0],[-0.77,-1.36]],"v":[[13.317,-1.089],[11.627,-0.029],[15.017,4.811],[16.667,3.641]],"c":true},"ix":2},"nm":"Path 6","mn":"ADBE Vector Shape - Group","hd":false},{"ind":6,"ty":"sh","ix":7,"ks":{"a":0,"k":{"i":[[0.35,-1.08],[0,0],[0,0],[0.18,-1.48],[1.87,0],[0,0],[0.82,0.05],[0,0],[0,0],[-0.4,0],[-0.13,0.92],[0,0],[-0.04,5.66],[0,0],[0.84,-1.1],[0,0],[-0.53,3.04],[0,0]],"o":[[0,0],[0,0],[-0.03,5.65],[-0.22,1.59],[0,0],[-0.46,-0.01],[0,0],[0,0],[0.48,0.02],[0.88,0],[0,0],[0.1,-1.45],[0,0],[-0.62,1.32],[0,0],[1.45,-2.11],[0,0],[-0.22,1.24]],"v":[[13.915,-6.345],[20.715,-6.345],[20.705,-3.015],[20.385,7.685],[17.235,10.065],[16.845,10.055],[14.905,9.955],[14.395,8.045],[15.575,8.095],[16.905,8.125],[18.425,6.745],[18.465,6.345],[18.665,-4.325],[13.145,-4.325],[10.985,-0.695],[9.735,-2.345],[12.725,-10.065],[14.795,-9.805]],"c":true},"ix":2},"nm":"Path 7","mn":"ADBE Vector Shape - Group","hd":false},{"ty":"mm","mm":1,"nm":"Merge Paths 1","mn":"ADBE Vector Filter - Merge","hd":false},{"ty":"fl","c":{"a":0,"k":[0.135000005364,0.140020996332,0.15000000596,1],"ix":4},"o":{"a":0,"k":100,"ix":5},"r":1,"nm":"Fill 1","mn":"ADBE Vector Graphic - Fill","hd":false},{"ty":"tr","p":{"a":0,"k":[0,0],"ix":2},"a":{"a":0,"k":[0,0],"ix":1},"s":{"a":0,"k":[100,100],"ix":3},"r":{"a":0,"k":0,"ix":6},"o":{"a":0,"k":100,"ix":7},"sk":{"a":0,"k":0,"ix":4},"sa":{"a":0,"k":0,"ix":5},"nm":"Transform"}],"nm":"我的","np":9,"cix":2,"ix":1,"mn":"ADBE Vector Group","hd":false}],"ip":0,"op":43,"st":1,"bm":0},{"ddd":0,"ind":3,"ty":4,"nm":"我的-未选中态","parent":1,"sr":1,"ks":{"o":{"a":1,"k":[{"i":{"x":[0.667],"y":[1]},"o":{"x":[0.333],"y":[0]},"n":["0p667_1_0p333_0"],"t":1,"s":[100],"e":[0]},{"i":{"x":[0.833],"y":[1]},"o":{"x":[0.333],"y":[0]},"n":["0p833_1_0p333_0"],"t":6,"s":[0],"e":[0]},{"i":{"x":[0.833],"y":[1]},"o":{"x":[0.167],"y":[0]},"n":["0p833_1_0p167_0"],"t":36,"s":[0],"e":[100]},{"t":41}],"ix":11},"r":{"a":0,"k":0,"ix":10},"p":{"a":0,"k":[92.967,111.058,0],"ix":2},"a":{"a":0,"k":[0,0,0],"ix":1},"s":{"a":0,"k":[100,100,100],"ix":6}},"ao":0,"shapes":[{"ty":"gr","it":[{"ind":0,"ty":"sh","ix":1,"ks":{"a":0,"k":{"i":[[0,0],[1.42,-0.37],[0,0],[0,0],[-0.31,-1.26],[-0.26,-0.74],[2.14,-0.8],[0,0],[-1.57,1.41],[-0.44,-0.59],[-0.89,0],[-0.52,3.13],[0,0],[0,0],[0.41,-0.02],[0.64,0.94],[0,0],[0.31,0.75],[-1,2.07],[0,0],[1.06,-1.28],[0.11,0.44],[0,0],[0.16,1.59],[0,0],[0,0],[0,0],[0.03,2.23],[0,0],[-0.13,-1.79],[0,0],[0,0],[-1.01,0.35],[0,0],[3.11,-0.35],[0,0],[-1.16,0.25],[0,0],[0,0],[0,0],[0,0],[0,0],[1.6,-0.26],[0,0],[-1.4,0.31],[0,0],[0.61,0],[0.77,0.06],[0,0],[0,0],[0,1.28],[0,0],[-1.27,0.42]],"o":[[-1.23,0.42],[0,0],[0,0],[0.17,1.68],[0.22,0.86],[-1.6,1.53],[0,0],[1.99,-0.8],[0.35,0.79],[1,1.33],[1.01,0],[0,0],[0,0],[-0.33,2.11],[-0.39,0],[0,0],[-0.35,-0.51],[1.38,-1.47],[0,0],[-0.78,1.63],[-0.12,-0.39],[0,0],[-0.27,-1.08],[0,0],[0,0],[0,0],[-0.13,-1.72],[0,0],[0,2.16],[0,0],[0,0],[1.14,-0.31],[0,0],[-2.41,0.95],[0,0],[1.25,-0.17],[0,0],[0,0],[0,0],[0,0],[0,0],[-1.42,0.3],[0,0],[1.49,-0.24],[0,0],[0,0.6],[-0.72,0],[0,0],[0,0],[1.33,0],[0,0],[1.4,-0.37],[0,0]],"v":[[-10.36,0.298],[-14.35,1.488],[-14.35,-2.482],[-8.96,-2.482],[-8.24,1.908],[-7.52,4.328],[-13.12,7.818],[-12.27,9.188],[-6.91,5.878],[-5.7,7.968],[-2.86,9.958],[-0.56,5.258],[-1.94,4.528],[-2.02,5.078],[-3.1,8.258],[-4.65,6.838],[-4.78,6.648],[-5.75,4.748],[-2.18,-0.562],[-3.54,-1.292],[-6.32,3.078],[-6.67,1.848],[-6.75,1.508],[-7.37,-2.482],[-0.73,-2.482],[-0.73,-4.002],[-7.5,-4.002],[-7.72,-9.912],[-9.29,-9.912],[-9.1,-4.002],[-14.35,-4.002],[-14.35,-7.312],[-11.11,-8.302],[-11.63,-9.802],[-19.91,-7.862],[-19.58,-6.342],[-15.97,-6.962],[-15.97,-4.002],[-20.48,-4.002],[-20.48,-2.482],[-15.97,-2.482],[-15.97,1.868],[-20.5,2.698],[-20.28,4.308],[-15.97,3.468],[-15.97,7.658],[-16.89,8.568],[-19.12,8.458],[-18.79,9.978],[-16.36,9.978],[-14.35,8.058],[-14.35,3.098],[-10.36,1.908]],"c":true},"ix":2},"nm":"Path 1","mn":"ADBE Vector Shape - Group","hd":false},{"ind":1,"ty":"sh","ix":2,"ks":{"a":0,"k":{"i":[[1.58,1.06],[0,0],[-0.96,-1.01],[0,0]],"o":[[0,0],[1.66,1.17],[0,0],[-1.1,-1.06]],"v":[[-5.309,-9.669],[-6.359,-8.659],[-2.439,-5.369],[-1.299,-6.519]],"c":true},"ix":2},"nm":"Path 2","mn":"ADBE Vector Shape - Group","hd":false},{"ind":2,"ty":"sh","ix":3,"ks":{"a":0,"k":{"i":[[0,0],[0,0],[-0.26,1.3],[0,0],[0.43,-1.24],[0,0],[0,0],[0,0],[0,0],[0,0],[0,0],[0,0]],"o":[[0,0],[0.44,-1.11],[0,0],[-0.2,1.32],[0,0],[0,0],[0,0],[0,0],[0,0],[0,0],[0,0],[0,0]],"v":[[9.184,-6.138],[5.654,-6.138],[6.684,-9.758],[5.114,-9.978],[4.174,-6.138],[2.134,-6.138],[2.134,9.532],[3.664,9.532],[3.664,7.642],[7.654,7.642],[7.654,8.902],[9.184,8.902]],"c":true},"ix":2},"nm":"Path 3","mn":"ADBE Vector Shape - Group","hd":false},{"ind":3,"ty":"sh","ix":4,"ks":{"a":0,"k":{"i":[[0,0],[0,0],[0,0],[0,0]],"o":[[0,0],[0,0],[0,0],[0,0]],"v":[[3.667,6.164],[3.667,1.334],[7.647,1.334],[7.647,6.164]],"c":true},"ix":2},"nm":"Path 4","mn":"ADBE Vector Shape - Group","hd":false},{"ind":4,"ty":"sh","ix":5,"ks":{"a":0,"k":{"i":[[0,0],[0,0],[0,0],[0,0]],"o":[[0,0],[0,0],[0,0],[0,0]],"v":[[3.667,-0.102],[3.667,-4.642],[7.647,-4.642],[7.647,-0.102]],"c":true},"ix":2},"nm":"Path 5","mn":"ADBE Vector Shape - Group","hd":false},{"ind":5,"ty":"sh","ix":6,"ks":{"a":0,"k":{"i":[[1.58,1.83],[0,0],[-0.9,-1.46],[0,0]],"o":[[0,0],[1.51,1.81],[0,0],[-0.83,-1.37]],"v":[[12.992,-1.025],[11.722,-0.235],[15.332,4.665],[16.582,3.785]],"c":true},"ix":2},"nm":"Path 6","mn":"ADBE Vector Shape - Group","hd":false},{"ind":6,"ty":"sh","ix":7,"ks":{"a":0,"k":{"i":[[0.4,-1.15],[0,0],[0,0],[0.17,-1.4],[1.84,0],[0,0],[0.76,0.03],[0,0],[0,0],[-0.48,0],[-0.18,1.13],[0,0],[-0.04,5.89],[0,0],[0.85,-1.13],[0,0],[-0.57,3.13],[0,0]],"o":[[0,0],[0,0],[-0.03,5.16],[-0.22,1.68],[0,0],[-0.44,-0.01],[0,0],[0,0],[0.61,0.02],[1.03,0],[0,0],[0.11,-1.49],[0,0],[-0.61,1.39],[0,0],[1.53,-2.16],[0,0],[-0.26,1.3]],"v":[[13.516,-6.12],[20.496,-6.12],[20.486,-2.4],[20.176,7.46],[17.106,10],[16.676,9.99],[14.876,9.91],[14.506,8.46],[15.256,8.49],[16.886,8.52],[18.686,6.82],[18.716,6.51],[18.946,-4.58],[12.926,-4.58],[10.736,-0.8],[9.796,-2.06],[12.926,-10],[14.476,-9.8]],"c":true},"ix":2},"nm":"Path 7","mn":"ADBE Vector Shape - Group","hd":false},{"ty":"mm","mm":1,"nm":"Merge Paths 1","mn":"ADBE Vector Filter - Merge","hd":false},{"ty":"fl","c":{"a":0,"k":[0.341176003218,0.343791007996,0.349020004272,1],"ix":4},"o":{"a":0,"k":100,"ix":5},"r":1,"nm":"Fill 1","mn":"ADBE Vector Graphic - Fill","hd":false},{"ty":"tr","p":{"a":0,"k":[0,0],"ix":2},"a":{"a":0,"k":[0,0],"ix":1},"s":{"a":0,"k":[100,100],"ix":3},"r":{"a":0,"k":0,"ix":6},"o":{"a":0,"k":100,"ix":7},"sk":{"a":0,"k":0,"ix":4},"sa":{"a":0,"k":0,"ix":5},"nm":"Transform"}],"nm":"我的","np":9,"cix":2,"ix":1,"mn":"ADBE Vector Group","hd":false}],"ip":0,"op":43,"st":1,"bm":0},{"ddd":0,"ind":4,"ty":3,"nm":"控制-我的","parent":1,"sr":1,"ks":{"o":{"a":0,"k":0,"ix":11},"r":{"a":0,"k":0,"ix":10},"p":{"s":true,"x":{"a":0,"k":92.992,"ix":3},"y":{"a":1,"k":[{"i":{"x":[0.591],"y":[1]},"o":{"x":[0.609],"y":[0]},"n":["0p591_1_0p609_0"],"t":1,"s":[72],"e":[49]},{"i":{"x":[0.654],"y":[1]},"o":{"x":[0.677],"y":[0]},"n":["0p654_1_0p677_0"],"t":6,"s":[49],"e":[56]},{"i":{"x":[0.667],"y":[1]},"o":{"x":[0.333],"y":[0]},"n":["0p667_1_0p333_0"],"t":10,"s":[56],"e":[56]},{"i":{"x":[0.191],"y":[1]},"o":{"x":[0.201],"y":[0]},"n":["0p191_1_0p201_0"],"t":36,"s":[56],"e":[72]},{"t":41}],"ix":4}},"a":{"a":0,"k":[0,0,0],"ix":1},"s":{"a":0,"k":[100,100,100],"ix":6}},"ao":0,"ip":0,"op":42,"st":-24,"bm":0},{"ddd":0,"ind":6,"ty":4,"nm":"耳朵01","parent":4,"sr":1,"ks":{"o":{"a":0,"k":100,"ix":11},"r":{"a":1,"k":[{"i":{"x":[0.667],"y":[1]},"o":{"x":[0.333],"y":[0]},"n":["0p667_1_0p333_0"],"t":6,"s":[0],"e":[-25]},{"i":{"x":[0.667],"y":[1]},"o":{"x":[0.333],"y":[0]},"n":["0p667_1_0p333_0"],"t":9,"s":[-25],"e":[0]},{"t":13}],"ix":10},"p":{"a":0,"k":[-4.992,-6,0],"ix":2},"a":{"a":0,"k":[7.094,1.29,0],"ix":1},"s":{"a":0,"k":[100,100,100],"ix":6}},"ao":0,"shapes":[{"ty":"gr","it":[{"ind":0,"ty":"sh","ix":1,"ks":{"a":0,"k":{"i":[[1.95,0.19],[1.45,2.01],[-0.8,1.98],[-0.91,0.44],[-0.46,0.1],[-0.68,0.05],[0,0],[0,0],[-0.86,-1.89],[0.86,-1.77]],"o":[[-2.62,-0.66],[-1.6,-2.19],[0.46,-1.15],[0.43,-0.21],[0.51,-0.11],[0,0],[0,0],[4.21,0],[0.86,1.9],[-0.86,1.76]],"v":[[1.194,7.096],[-4.966,2.996],[-6.596,-4.094],[-4.446,-6.364],[-3.126,-6.814],[-1.376,-7.054],[-1.036,-7.084],[-0.526,-7.114],[6.264,-2.804],[6.264,4.126]],"c":true},"ix":2},"nm":"Path 1","mn":"ADBE Vector Shape - Group","hd":false},{"ty":"fl","c":{"a":0,"k":[0.133332997561,0.141176000237,0.149020001292,1],"ix":4},"o":{"a":0,"k":100,"ix":5},"r":1,"nm":"Fill 1","mn":"ADBE Vector Graphic - Fill","hd":false},{"ty":"tr","p":{"a":0,"k":[0,0],"ix":2},"a":{"a":0,"k":[0,0],"ix":1},"s":{"a":0,"k":[100,100],"ix":3},"r":{"a":0,"k":0,"ix":6},"o":{"a":0,"k":100,"ix":7},"sk":{"a":0,"k":0,"ix":4},"sa":{"a":0,"k":0,"ix":5},"nm":"Transform"}],"nm":"耳朵","np":2,"cix":2,"ix":1,"mn":"ADBE Vector Group","hd":false}],"ip":6,"op":36,"st":20,"bm":0},{"ddd":0,"ind":7,"ty":4,"nm":"耳朵02","parent":4,"sr":1,"ks":{"o":{"a":0,"k":100,"ix":11},"r":{"a":1,"k":[{"i":{"x":[0.667],"y":[1]},"o":{"x":[0.333],"y":[0]},"n":["0p667_1_0p333_0"],"t":6,"s":[0],"e":[25]},{"i":{"x":[0.667],"y":[1]},"o":{"x":[0.333],"y":[0]},"n":["0p667_1_0p333_0"],"t":9,"s":[25],"e":[0]},{"t":13}],"ix":10},"p":{"a":0,"k":[-4.992,-6,0],"ix":2},"a":{"a":0,"k":[0.741,7.878,0],"ix":1},"s":{"a":0,"k":[100,100,100],"ix":6}},"ao":0,"shapes":[{"ty":"gr","it":[{"ind":0,"ty":"sh","ix":1,"ks":{"a":0,"k":{"i":[[1.175,-0.102],[1,0.406],[0.598,0.936],[0,0],[-0.08,0.93],[-0.2,0.42],[-1.56,0.04],[0,0],[-0.25,-0.03],[-0.43,-0.12],[-1.02,-0.6],[-0.81,-2.25],[0,0],[2.681,-1.935]],"o":[[-1.146,0.101],[-1.975,-0.803],[-1.16,-1.79],[-0.16,-1.06],[0.04,-0.47],[0.92,-1.96],[0,0],[0.25,0],[0.37,0.05],[1.05,0.28],[2.12,1.23],[0,0],[0,0],[-0.674,0.486]],"v":[[0.78,5.27],[-1.069,6.56],[-5.196,3.338],[-6.876,-0.522],[-7.006,-3.472],[-6.636,-4.812],[-3.486,-7.112],[-2.936,-7.122],[-2.196,-7.072],[-0.966,-6.812],[2.184,-5.502],[6.734,-0.262],[6.844,0.058],[3.22,3.992]],"c":true},"ix":2},"nm":"Path 1","mn":"ADBE Vector Shape - Group","hd":false},{"ty":"fl","c":{"a":0,"k":[0.133332997561,0.141176000237,0.149020001292,1],"ix":4},"o":{"a":0,"k":100,"ix":5},"r":1,"nm":"Fill 1","mn":"ADBE Vector Graphic - Fill","hd":false},{"ty":"tr","p":{"a":0,"k":[0,0],"ix":2},"a":{"a":0,"k":[0,0],"ix":1},"s":{"a":0,"k":[100,100],"ix":3},"r":{"a":0,"k":0,"ix":6},"o":{"a":0,"k":100,"ix":7},"sk":{"a":0,"k":0,"ix":4},"sa":{"a":0,"k":0,"ix":5},"nm":"Transform"}],"nm":"耳朵","np":2,"cix":2,"ix":1,"mn":"ADBE Vector Group","hd":false}],"ip":6,"op":36,"st":20,"bm":0},{"ddd":0,"ind":8,"ty":4,"nm":"非完整身体-选中态","parent":4,"sr":1,"ks":{"o":{"a":0,"k":100,"ix":11},"r":{"a":0,"k":0,"ix":10},"p":{"a":0,"k":[1.47,2.96,0],"ix":2},"a":{"a":0,"k":[0,0,0],"ix":1},"s":{"a":0,"k":[100,100,100],"ix":6}},"ao":0,"shapes":[{"ty":"gr","it":[{"ind":0,"ty":"sh","ix":1,"ks":{"a":0,"k":{"i":[[0,0],[-0.09,-0.12],[19.46,-0.07],[0.38,3.53],[-0.65,1.29],[0.05,1.53],[-3.41,2.79],[0,0],[0,0],[-2.14,-0.19],[-1.79,-0.1],[0,0],[-0.41,-0.02],[0,0],[-0.16,-2.01],[0,0],[0,0],[0.15,-0.82],[0.79,-1.37],[3.04,-1.07],[0,0]],"o":[[0.54,1.13],[2.56,3.57],[-12.82,0],[-0.16,-1.44],[0.3,-0.58],[-2.02,-3.8],[3.41,-2.8],[0,0],[1.4,0.23],[1.66,0.14],[0,0],[0.45,0.02],[0,0],[2.03,0.07],[0,0],[0,0],[-0.01,0.57],[-0.27,1.44],[-1.48,2.56],[0,0],[0,0]],"v":[[9.712,1.021],[13.412,4.871],[-2.068,17.041],[-18.498,9.041],[-17.688,4.961],[-12.368,-3.159],[-10.328,-14.979],[-0.358,-16.779],[0.172,-16.689],[5.542,-16.059],[10.762,-15.689],[11.832,-15.629],[13.132,-15.559],[14.692,-15.489],[18.522,-11.819],[18.532,-11.619],[18.542,-11.339],[18.322,-9.229],[16.762,-4.969],[9.962,0.581],[9.572,0.711]],"c":true},"ix":2},"nm":"Path 1","mn":"ADBE Vector Shape - Group","hd":false},{"ind":1,"ty":"sh","ix":2,"ks":{"a":1,"k":[{"i":{"x":0.833,"y":0.833},"o":{"x":0.167,"y":0.167},"n":"0p833_0p833_0p167_0p167","t":13,"s":[{"i":[[1.66,0],[0,-1.66],[-1.66,0],[0,1.66]],"o":[[-1.66,0],[0,1.66],[1.66,0],[0,-1.66]],"v":[[-2.462,-9.96],[-5.462,-6.96],[-2.462,-3.96],[0.538,-6.96]],"c":true}],"e":[{"i":[[1.66,0],[0,-0.766],[-1.66,0],[0,0.844]],"o":[[-1.66,0],[0,0.875],[1.66,0],[0,-0.859]],"v":[[-2.462,-6.679],[-5.462,-6.96],[-2.462,-5.931],[0.538,-6.96]],"c":true}]},{"i":{"x":0.833,"y":0.833},"o":{"x":0.167,"y":0.167},"n":"0p833_0p833_0p167_0p167","t":15,"s":[{"i":[[1.66,0],[0,-0.766],[-1.66,0],[0,0.844]],"o":[[-1.66,0],[0,0.875],[1.66,0],[0,-0.859]],"v":[[-2.462,-6.679],[-5.462,-6.96],[-2.462,-5.931],[0.538,-6.96]],"c":true}],"e":[{"i":[[1.66,0],[0,-1.66],[-1.66,0],[0,1.66]],"o":[[-1.66,0],[0,1.66],[1.66,0],[0,-1.66]],"v":[[-2.462,-9.96],[-5.462,-6.96],[-2.462,-3.96],[0.538,-6.96]],"c":true}]},{"t":17}],"ix":2},"nm":"Path 2","mn":"ADBE Vector Shape - Group","hd":false},{"ty":"fl","c":{"a":0,"k":[0.133332997561,0.141176000237,0.149020001292,1],"ix":4},"o":{"a":0,"k":100,"ix":5},"r":1,"nm":"Fill 1","mn":"ADBE Vector Graphic - Fill","hd":false},{"ty":"tr","p":{"a":0,"k":[0,0],"ix":2},"a":{"a":0,"k":[0,0],"ix":1},"s":{"a":0,"k":[100,100],"ix":3},"r":{"a":0,"k":0,"ix":6},"o":{"a":0,"k":100,"ix":7},"sk":{"a":0,"k":0,"ix":4},"sa":{"a":0,"k":0,"ix":5},"nm":"Transform"}],"nm":"路径","np":3,"cix":2,"ix":1,"mn":"ADBE Vector Group","hd":false}],"ip":6,"op":36,"st":20,"bm":0},{"ddd":0,"ind":9,"ty":4,"nm":"完整身体-选中态","parent":4,"sr":1,"ks":{"o":{"a":1,"k":[{"i":{"x":[0.591],"y":[1]},"o":{"x":[0.605],"y":[0]},"n":["0p591_1_0p605_0"],"t":1,"s":[0],"e":[100]},{"i":{"x":[0.833],"y":[1]},"o":{"x":[0.333],"y":[0]},"n":["0p833_1_0p333_0"],"t":6,"s":[100],"e":[100]},{"i":{"x":[0.191],"y":[1]},"o":{"x":[0.209],"y":[0]},"n":["0p191_1_0p209_0"],"t":36,"s":[100],"e":[0]},{"t":41}],"ix":11},"r":{"a":0,"k":0,"ix":10},"p":{"a":0,"k":[-0.008,19.992,0],"ix":2},"a":{"a":0,"k":[-0.516,20.492,0],"ix":1},"s":{"a":1,"k":[{"i":{"x":[0.586,0.586,0.667],"y":[1,1,1]},"o":{"x":[0.609,0.609,0.333],"y":[0,0,0]},"n":["0p586_1_0p609_0","0p586_1_0p609_0","0p667_1_0p333_0"],"t":1,"s":[30,30,100],"e":[100,100,100]},{"t":6}],"ix":6}},"ao":0,"shapes":[{"ty":"gr","it":[{"ind":0,"ty":"sh","ix":1,"ks":{"a":0,"k":{"i":[[0,0],[-0.08,-0.12],[19.46,-0.07],[0.38,3.53],[-0.66,1.29],[0.05,1.52],[1.45,2],[-0.8,1.98],[-0.91,0.45],[-0.46,0.11],[-0.68,0.06],[0,0],[0,0],[-0.08,0.93],[-0.2,0.42],[-1.55,0.04],[0,0],[-0.25,-0.03],[-0.44,-0.12],[-1.03,-0.6],[-0.82,-2.25],[0,0],[0,0],[-2.14,-0.19],[-1.78,-0.1],[0,0],[-0.41,-0.02],[0,0],[-0.16,-2.01],[0,0],[0,0],[0.15,-0.82],[0.8,-1.37],[3.04,-1.07],[0,0]],"o":[[0.53,1.13],[2.56,3.57],[-12.83,0],[-0.15,-1.44],[0.3,-0.58],[-2.62,-0.66],[-1.6,-2.2],[0.46,-1.15],[0.43,-0.21],[0.51,-0.11],[0,0],[0,0],[-0.16,-1.06],[0.05,-0.47],[0.92,-1.96],[0,0],[0.25,0],[0.38,0.05],[1.04,0.28],[2.11,1.23],[0,0],[0,0],[1.41,0.22],[1.66,0.14],[0,0],[0.45,0.03],[0,0],[2.03,0.07],[0,0],[0,0],[-0.01,0.57],[-0.27,1.44],[-1.48,2.56],[0,0],[0,0]],"v":[[10.68,4.48],[14.37,8.33],[-1.1,20.5],[-17.54,12.5],[-16.72,8.42],[-11.4,0.31],[-17.56,-3.79],[-19.19,-10.88],[-17.04,-13.16],[-15.72,-13.61],[-13.97,-13.85],[-13.63,-13.87],[-13.12,-13.9],[-13.25,-16.85],[-12.88,-18.19],[-9.73,-20.49],[-9.18,-20.5],[-8.44,-20.45],[-7.2,-20.19],[-4.05,-18.88],[0.5,-13.64],[0.61,-13.32],[1.13,-13.22],[6.51,-12.6],[11.72,-12.23],[12.8,-12.17],[14.09,-12.1],[15.65,-12.03],[19.49,-8.36],[19.5,-8.16],[19.5,-7.88],[19.28,-5.77],[17.72,-1.51],[10.92,4.04],[10.54,4.17]],"c":true},"ix":2},"nm":"Path 1","mn":"ADBE Vector Shape - Group","hd":false},{"ind":1,"ty":"sh","ix":2,"ks":{"a":0,"k":{"i":[[1.66,0],[0,-1.66],[-1.66,0],[0,1.66]],"o":[[-1.66,0],[0,1.66],[1.66,0],[0,-1.66]],"v":[[-1.5,-6.5],[-4.5,-3.5],[-1.5,-0.5],[1.5,-3.5]],"c":true},"ix":2},"nm":"Path 2","mn":"ADBE Vector Shape - Group","hd":false},{"ty":"mm","mm":1,"nm":"Merge Paths 1","mn":"ADBE Vector Filter - Merge","hd":false},{"ty":"fl","c":{"a":0,"k":[0.133332997561,0.141176000237,0.149020001292,1],"ix":4},"o":{"a":0,"k":100,"ix":5},"r":1,"nm":"Fill 1","mn":"ADBE Vector Graphic - Fill","hd":false},{"ty":"tr","p":{"a":0,"k":[0,0],"ix":2},"a":{"a":0,"k":[0,0],"ix":1},"s":{"a":0,"k":[100,100],"ix":3},"r":{"a":0,"k":0,"ix":6},"o":{"a":0,"k":100,"ix":7},"sk":{"a":0,"k":0,"ix":4},"sa":{"a":0,"k":0,"ix":5},"nm":"Transform"}],"nm":"路径","np":4,"cix":2,"ix":1,"mn":"ADBE Vector Group","hd":false}],"ip":36,"op":42,"st":1,"bm":0},{"ddd":0,"ind":10,"ty":4,"nm":"完整身体-选中态","parent":4,"sr":1,"ks":{"o":{"a":1,"k":[{"i":{"x":[0.591],"y":[1]},"o":{"x":[0.605],"y":[0]},"n":["0p591_1_0p605_0"],"t":1,"s":[0],"e":[100]},{"t":6}],"ix":11},"r":{"a":0,"k":0,"ix":10},"p":{"a":0,"k":[-0.008,19.992,0],"ix":2},"a":{"a":0,"k":[-0.516,20.492,0],"ix":1},"s":{"a":1,"k":[{"i":{"x":[0.586,0.586,0.667],"y":[1,1,1]},"o":{"x":[0.609,0.609,0.333],"y":[0,0,0]},"n":["0p586_1_0p609_0","0p586_1_0p609_0","0p667_1_0p333_0"],"t":1,"s":[30,30,100],"e":[100,100,100]},{"t":6}],"ix":6}},"ao":0,"shapes":[{"ty":"gr","it":[{"ind":0,"ty":"sh","ix":1,"ks":{"a":0,"k":{"i":[[0,0],[-0.08,-0.12],[19.46,-0.07],[0.38,3.53],[-0.66,1.29],[0.05,1.52],[1.45,2],[-0.8,1.98],[-0.91,0.45],[-0.46,0.11],[-0.68,0.06],[0,0],[0,0],[-0.08,0.93],[-0.2,0.42],[-1.55,0.04],[0,0],[-0.25,-0.03],[-0.44,-0.12],[-1.03,-0.6],[-0.82,-2.25],[0,0],[0,0],[-2.14,-0.19],[-1.78,-0.1],[0,0],[-0.41,-0.02],[0,0],[-0.16,-2.01],[0,0],[0,0],[0.15,-0.82],[0.8,-1.37],[3.04,-1.07],[0,0]],"o":[[0.53,1.13],[2.56,3.57],[-12.83,0],[-0.15,-1.44],[0.3,-0.58],[-2.62,-0.66],[-1.6,-2.2],[0.46,-1.15],[0.43,-0.21],[0.51,-0.11],[0,0],[0,0],[-0.16,-1.06],[0.05,-0.47],[0.92,-1.96],[0,0],[0.25,0],[0.38,0.05],[1.04,0.28],[2.11,1.23],[0,0],[0,0],[1.41,0.22],[1.66,0.14],[0,0],[0.45,0.03],[0,0],[2.03,0.07],[0,0],[0,0],[-0.01,0.57],[-0.27,1.44],[-1.48,2.56],[0,0],[0,0]],"v":[[10.68,4.48],[14.37,8.33],[-1.1,20.5],[-17.54,12.5],[-16.72,8.42],[-11.4,0.31],[-17.56,-3.79],[-19.19,-10.88],[-17.04,-13.16],[-15.72,-13.61],[-13.97,-13.85],[-13.63,-13.87],[-13.12,-13.9],[-13.25,-16.85],[-12.88,-18.19],[-9.73,-20.49],[-9.18,-20.5],[-8.44,-20.45],[-7.2,-20.19],[-4.05,-18.88],[0.5,-13.64],[0.61,-13.32],[1.13,-13.22],[6.51,-12.6],[11.72,-12.23],[12.8,-12.17],[14.09,-12.1],[15.65,-12.03],[19.49,-8.36],[19.5,-8.16],[19.5,-7.88],[19.28,-5.77],[17.72,-1.51],[10.92,4.04],[10.54,4.17]],"c":true},"ix":2},"nm":"Path 1","mn":"ADBE Vector Shape - Group","hd":false},{"ind":1,"ty":"sh","ix":2,"ks":{"a":0,"k":{"i":[[1.66,0],[0,-1.66],[-1.66,0],[0,1.66]],"o":[[-1.66,0],[0,1.66],[1.66,0],[0,-1.66]],"v":[[-1.5,-6.5],[-4.5,-3.5],[-1.5,-0.5],[1.5,-3.5]],"c":true},"ix":2},"nm":"Path 2","mn":"ADBE Vector Shape - Group","hd":false},{"ty":"mm","mm":1,"nm":"Merge Paths 1","mn":"ADBE Vector Filter - Merge","hd":false},{"ty":"fl","c":{"a":0,"k":[0.133332997561,0.141176000237,0.149020001292,1],"ix":4},"o":{"a":0,"k":100,"ix":5},"r":1,"nm":"Fill 1","mn":"ADBE Vector Graphic - Fill","hd":false},{"ty":"tr","p":{"a":0,"k":[0,0],"ix":2},"a":{"a":0,"k":[0,0],"ix":1},"s":{"a":0,"k":[100,100],"ix":3},"r":{"a":0,"k":0,"ix":6},"o":{"a":0,"k":100,"ix":7},"sk":{"a":0,"k":0,"ix":4},"sa":{"a":0,"k":0,"ix":5},"nm":"Transform"}],"nm":"路径","np":4,"cix":2,"ix":1,"mn":"ADBE Vector Group","hd":false}],"ip":0,"op":6,"st":1,"bm":0},{"ddd":0,"ind":11,"ty":4,"nm":"眼睛","parent":4,"sr":1,"ks":{"o":{"a":1,"k":[{"i":{"x":[0.399],"y":[1]},"o":{"x":[0.413],"y":[0]},"n":["0p399_1_0p413_0"],"t":1,"s":[100],"e":[0]},{"i":{"x":[0.667],"y":[1]},"o":{"x":[0.333],"y":[0]},"n":["0p667_1_0p333_0"],"t":6,"s":[0],"e":[0]},{"i":{"x":[0.667],"y":[1]},"o":{"x":[0.333],"y":[0]},"n":["0p667_1_0p333_0"],"t":36,"s":[0],"e":[100]},{"t":41}],"ix":11},"r":{"a":0,"k":0,"ix":10},"p":{"a":0,"k":[-0.992,-4,0],"ix":2},"a":{"a":0,"k":[0,0,0],"ix":1},"s":{"a":0,"k":[100,100,100],"ix":6}},"ao":0,"shapes":[{"ty":"gr","it":[{"d":1,"ty":"el","s":{"a":0,"k":[6,6],"ix":2},"p":{"a":0,"k":[0,0],"ix":3},"nm":"Ellipse Path 1","mn":"ADBE Vector Shape - Ellipse","hd":false},{"ty":"fl","c":{"a":0,"k":[0.341176003218,0.343791007996,0.349020004272,1],"ix":4},"o":{"a":0,"k":100,"ix":5},"r":1,"nm":"Fill 1","mn":"ADBE Vector Graphic - Fill","hd":false},{"ty":"tr","p":{"a":0,"k":[0,0],"ix":2},"a":{"a":0,"k":[0,0],"ix":1},"s":{"a":0,"k":[100,100],"ix":3},"r":{"a":0,"k":0,"ix":6},"o":{"a":0,"k":100,"ix":7},"sk":{"a":0,"k":0,"ix":4},"sa":{"a":0,"k":0,"ix":5},"nm":"Transform"}],"nm":"椭圆形","np":2,"cix":2,"ix":1,"mn":"ADBE Vector Group","hd":false}],"ip":0,"op":42,"st":1,"bm":0},{"ddd":0,"ind":12,"ty":4,"nm":"袋鼠","parent":4,"sr":1,"ks":{"o":{"a":1,"k":[{"i":{"x":[0.399],"y":[1]},"o":{"x":[0.413],"y":[0]},"n":["0p399_1_0p413_0"],"t":1,"s":[100],"e":[0]},{"i":{"x":[0.667],"y":[1]},"o":{"x":[0.333],"y":[0]},"n":["0p667_1_0p333_0"],"t":6,"s":[0],"e":[0]},{"i":{"x":[0.667],"y":[1]},"o":{"x":[0.333],"y":[0]},"n":["0p667_1_0p333_0"],"t":36,"s":[0],"e":[100]},{"t":41}],"ix":11},"r":{"a":0,"k":0,"ix":10},"p":{"a":0,"k":[0.512,-0.5,0],"ix":2},"a":{"a":0,"k":[0,0,0],"ix":1},"s":{"a":0,"k":[100,100,100],"ix":6}},"ao":0,"shapes":[{"ty":"gr","it":[{"ind":0,"ty":"sh","ix":1,"ks":{"a":0,"k":{"i":[[0,0],[-0.09,-0.12],[19.46,-0.07],[0.38,3.53],[-0.66,1.29],[0.06,1.52],[1.46,2],[-0.8,1.98],[-0.91,0.45],[-0.46,0.11],[-0.68,0.06],[0,0],[0,0],[-0.08,0.93],[-0.2,0.42],[-1.56,0.04],[0,0],[-0.25,-0.03],[-0.43,-0.12],[-1.02,-0.6],[-0.81,-2.25],[0,0],[0,0],[-2.14,-0.19],[-1.79,-0.1],[0,0],[-0.41,-0.02],[0,0],[-0.16,-2.01],[0,0],[0,0],[0.15,-0.82],[0.8,-1.37],[3.04,-1.07],[0,0]],"o":[[0.54,1.13],[2.55,3.57],[-12.82,0],[-0.15,-1.44],[0.29,-0.58],[-2.61,-0.66],[-1.59,-2.2],[0.46,-1.15],[0.43,-0.21],[0.51,-0.11],[0,0],[0,0],[-0.16,-1.06],[0.04,-0.47],[0.92,-1.96],[0,0],[0.25,0],[0.37,0.05],[1.05,0.28],[2.12,1.23],[0,0],[0,0],[1.4,0.22],[1.66,0.14],[0,0],[0.45,0.03],[0,0],[2.04,0.07],[0,0],[0,0],[0,0.57],[-0.27,1.45],[-1.47,2.56],[0,0],[0,0]],"v":[[10.674,4.48],[14.374,8.33],[-1.106,20.5],[-17.536,12.5],[-16.716,8.42],[-11.406,0.31],[-17.566,-3.79],[-19.186,-10.88],[-17.036,-13.16],[-15.716,-13.61],[-13.966,-13.85],[-13.626,-13.87],[-13.116,-13.9],[-13.246,-16.85],[-12.876,-18.19],[-9.726,-20.49],[-9.176,-20.5],[-8.436,-20.45],[-7.206,-20.19],[-4.056,-18.88],[0.494,-13.64],[0.604,-13.32],[1.134,-13.22],[6.504,-12.6],[11.724,-12.23],[12.794,-12.17],[14.084,-12.1],[15.644,-12.03],[19.484,-8.36],[19.494,-8.15],[19.494,-7.87],[19.274,-5.77],[17.714,-1.51],[10.924,4.04],[10.534,4.17]],"c":true},"ix":2},"nm":"Path 1","mn":"ADBE Vector Shape - Group","hd":false},{"ind":1,"ty":"sh","ix":2,"ks":{"a":0,"k":{"i":[[1.02,1.43],[0,3.27],[-0.06,1.48],[0,0],[0,0],[1.72,1.22],[0.08,-0.17],[0.63,0],[0,0],[0.19,-0.45],[-6.64,0],[-0.41,-3.78],[-10.65,-0.02],[-0.43,0.21]],"o":[[-2.85,-3.17],[8.81,-0.5],[0,0],[0,0],[-4.49,-0.23],[0,-5.36],[-0.23,2.57],[0,0],[-3.08,0.03],[-0.21,0.53],[2.8,9.2],[0.2,1.84],[6.93,0],[1.62,-0.79]],"v":[[11.116,10.65],[5.836,0.98],[15.486,-7.74],[15.496,-8.04],[13.316,-8.13],[-2.924,-10.22],[-9.264,-16.48],[-8.454,-9.98],[-10.064,-9.98],[-15.484,-9.39],[-8.034,-3.3],[-13.554,12.08],[-1.104,16.5],[9.556,15.12]],"c":true},"ix":2},"nm":"Path 2","mn":"ADBE Vector Shape - Group","hd":false},{"ty":"mm","mm":1,"nm":"Merge Paths 1","mn":"ADBE Vector Filter - Merge","hd":false},{"ty":"fl","c":{"a":0,"k":[0.341176003218,0.345097988844,0.349020004272,1],"ix":4},"o":{"a":0,"k":100,"ix":5},"r":1,"nm":"Fill 1","mn":"ADBE Vector Graphic - Fill","hd":false},{"ty":"tr","p":{"a":0,"k":[0,0],"ix":2},"a":{"a":0,"k":[0,0],"ix":1},"s":{"a":0,"k":[100,100],"ix":3},"r":{"a":0,"k":0,"ix":6},"o":{"a":0,"k":100,"ix":7},"sk":{"a":0,"k":0,"ix":4},"sa":{"a":0,"k":0,"ix":5},"nm":"Transform"}],"nm":"Combined Shape","np":4,"cix":2,"ix":1,"mn":"ADBE Vector Group","hd":false}],"ip":0,"op":42,"st":1,"bm":0},{"ddd":0,"ind":13,"ty":4,"nm":"椭圆","parent":4,"sr":1,"ks":{"o":{"a":1,"k":[{"i":{"x":[0.587],"y":[1]},"o":{"x":[0.605],"y":[0]},"n":["0p587_1_0p605_0"],"t":1,"s":[15],"e":[100]},{"i":{"x":[0.697],"y":[1]},"o":{"x":[0.157],"y":[0]},"n":["0p697_1_0p157_0"],"t":6,"s":[100],"e":[100]},{"i":{"x":[0.833],"y":[1]},"o":{"x":[0.428],"y":[0]},"n":["0p833_1_0p428_0"],"t":36,"s":[100],"e":[0]},{"t":41}],"ix":11},"r":{"a":0,"k":0,"ix":10},"p":{"a":0,"k":[0.008,0,0],"ix":2},"a":{"a":0,"k":[0,0,0],"ix":1},"s":{"a":0,"k":[100,100,100],"ix":6}},"ao":0,"shapes":[{"ty":"gr","it":[{"d":1,"ty":"el","s":{"a":0,"k":[68,68],"ix":2},"p":{"a":0,"k":[0,0],"ix":3},"nm":"Ellipse Path 1","mn":"ADBE Vector Shape - Ellipse","hd":false},{"ty":"gf","o":{"a":0,"k":100,"ix":10},"r":1,"g":{"p":3,"k":{"a":0,"k":[0,1,0.883,0.3,0.5,1,0.825,0.3,1,1,0.767,0.3],"ix":9}},"s":{"a":0,"k":[-24.743,-20.859],"ix":5},"e":{"a":0,"k":[23.105,23.679],"ix":6},"t":1,"nm":"Gradient Fill 1","mn":"ADBE Vector Graphic - G-Fill","hd":false},{"ty":"tr","p":{"a":0,"k":[0,0],"ix":2},"a":{"a":0,"k":[0,0],"ix":1},"s":{"a":0,"k":[100,100],"ix":3},"r":{"a":0,"k":0,"ix":6},"o":{"a":0,"k":100,"ix":7},"sk":{"a":0,"k":0,"ix":4},"sa":{"a":0,"k":0,"ix":5},"nm":"Transform"}],"nm":"椭圆形备份 4","np":2,"cix":2,"ix":1,"mn":"ADBE Vector Group","hd":false}],"ip":1,"op":42,"st":1,"bm":0},{"ddd":0,"ind":14,"ty":4,"nm":"白底","parent":1,"sr":1,"ks":{"o":{"a":0,"k":100,"ix":11},"r":{"a":0,"k":0,"ix":10},"p":{"a":0,"k":[93,94,0],"ix":2},"a":{"a":0,"k":[0,0,0],"ix":1},"s":{"a":0,"k":[100,100,100],"ix":6}},"ao":0,"shapes":[{"ty":"gr","it":[{"ind":0,"ty":"sh","ix":1,"ks":{"a":1,"k":[{"i":{"x":0.667,"y":1},"o":{"x":0.632,"y":0},"n":"0p667_1_0p632_0","t":1,"s":[{"i":[[0,0.116],[-6.105,0],[-2.453,0],[0,0],[-10.22,0.13],[0,0],[-10.87,0],[0,0],[-3.744,0],[-16.46,0],[0,-3.004],[0,0],[0,0],[0,16.657]],"o":[[14.75,-0.016],[3.969,0],[0,0],[7.75,0],[0,0],[10.17,0],[0,0],[2.89,0],[10.131,0],[0,0.309],[0,26.184],[0,0],[0,0],[0,-1.022]],"v":[[-93,-65],[-42.02,-65.028],[-31.422,-65.045],[-31,-65.037],[-0.52,-65.005],[0,-65.005],[30.62,-65.04],[31.485,-65.045],[41.994,-65.02],[93,-65],[156.25,-62.125],[148.5,68.5],[-148.5,71.5],[-156.844,-61.422]],"c":true}],"e":[{"i":[[0,0.023],[-5.245,2.887],[-3.01,2.96],[0,0],[-10.22,0.13],[0,0],[-8.75,-8.63],[0,0],[-3.622,-1.527],[-16.46,0],[0,-0.433],[0,0],[0,0],[0,5.273]],"o":[[14.75,-0.016],[3.477,-1.914],[0,0],[8.65,-8.79],[0,0],[10.17,0],[0,0],[3.01,2.96],[10.628,2.255],[0,0.104],[0,12.058],[0,0],[0,0],[0,-0.063]],"v":[[-93,-65],[-42.005,-71.012],[-31.43,-80.779],[-31,-81.209],[-0.51,-93.989],[0,-93.989],[30.56,-81.649],[31.43,-80.779],[41.997,-71.005],[93,-65],[150.875,-66.939],[151.5,77.5],[-146,67],[-137.562,-58.871]],"c":true}]},{"i":{"x":0.667,"y":1},"o":{"x":0.333,"y":0},"n":"0p667_1_0p333_0","t":6,"s":[{"i":[[0,0.023],[-5.245,2.887],[-3.01,2.96],[0,0],[-10.22,0.13],[0,0],[-8.75,-8.63],[0,0],[-3.622,-1.527],[-16.46,0],[0,-0.433],[0,0],[0,0],[0,5.273]],"o":[[14.75,-0.016],[3.477,-1.914],[0,0],[8.65,-8.79],[0,0],[10.17,0],[0,0],[3.01,2.96],[10.628,2.255],[0,0.104],[0,12.058],[0,0],[0,0],[0,-0.063]],"v":[[-93,-65],[-42.005,-71.012],[-31.43,-80.779],[-31,-81.209],[-0.51,-93.989],[0,-93.989],[30.56,-81.649],[31.43,-80.779],[41.997,-71.005],[93,-65],[150.875,-66.939],[151.5,77.5],[-146,67],[-137.562,-58.871]],"c":true}],"e":[{"i":[[0,0.023],[-16.46,0],[-3.01,2.96],[0,0],[-10.22,0.13],[0,0],[-8.75,-8.63],[0,0],[-6.14,0],[-16.46,0],[0,-0.433],[0,0],[0,0],[0,5.273]],"o":[[16.46,0],[6.14,0],[0,0],[8.65,-8.79],[0,0],[10.17,0],[0,0],[3.01,2.96],[16.46,0],[0,0.104],[0,12.058],[0,0],[0,0],[0,-0.063]],"v":[[-93,-65],[-43.63,-65],[-31.43,-69.79],[-31,-70.22],[-0.51,-83],[0,-83],[30.56,-70.66],[31.43,-69.79],[43.63,-65],[93,-65],[143,-64.314],[134.5,81],[-148,77.5],[-149,-58.418]],"c":true}]},{"i":{"x":0.833,"y":1},"o":{"x":0.333,"y":0},"n":"0p833_1_0p333_0","t":10,"s":[{"i":[[0,0.023],[-16.46,0],[-3.01,2.96],[0,0],[-10.22,0.13],[0,0],[-8.75,-8.63],[0,0],[-6.14,0],[-16.46,0],[0,-0.433],[0,0],[0,0],[0,5.273]],"o":[[16.46,0],[6.14,0],[0,0],[8.65,-8.79],[0,0],[10.17,0],[0,0],[3.01,2.96],[16.46,0],[0,0.104],[0,12.058],[0,0],[0,0],[0,-0.063]],"v":[[-93,-65],[-43.63,-65],[-31.43,-69.79],[-31,-70.22],[-0.51,-83],[0,-83],[30.56,-70.66],[31.43,-69.79],[43.63,-65],[93,-65],[143,-64.314],[134.5,81],[-148,77.5],[-149,-58.418]],"c":true}],"e":[{"i":[[0,0.023],[-16.46,0],[-3.01,2.96],[0,0],[-10.22,0.13],[0,0],[-8.75,-8.63],[0,0],[-6.14,0],[-16.46,0],[0,-0.433],[0,0],[0,0],[0,5.273]],"o":[[16.46,0],[6.14,0],[0,0],[8.65,-8.79],[0,0],[10.17,0],[0,0],[3.01,2.96],[16.46,0],[0,0.104],[0,12.058],[0,0],[0,0],[0,-0.063]],"v":[[-93,-65],[-43.63,-65],[-31.43,-69.79],[-31,-70.22],[-0.51,-83],[0,-83],[30.56,-70.66],[31.43,-69.79],[43.63,-65],[93,-65],[136.125,-68.814],[136.5,83.5],[-138.5,81.5],[-150.219,-51.183]],"c":true}]},{"i":{"x":0.667,"y":1},"o":{"x":0.167,"y":0},"n":"0p667_1_0p167_0","t":36,"s":[{"i":[[0,0.023],[-16.46,0],[-3.01,2.96],[0,0],[-10.22,0.13],[0,0],[-8.75,-8.63],[0,0],[-6.14,0],[-16.46,0],[0,-0.433],[0,0],[0,0],[0,5.273]],"o":[[16.46,0],[6.14,0],[0,0],[8.65,-8.79],[0,0],[10.17,0],[0,0],[3.01,2.96],[16.46,0],[0,0.104],[0,12.058],[0,0],[0,0],[0,-0.063]],"v":[[-93,-65],[-43.63,-65],[-31.43,-69.79],[-31,-70.22],[-0.51,-83],[0,-83],[30.56,-70.66],[31.43,-69.79],[43.63,-65],[93,-65],[136.125,-68.814],[136.5,83.5],[-138.5,81.5],[-150.219,-51.183]],"c":true}],"e":[{"i":[[0,0.023],[-6.105,0],[-2.453,0],[0,0],[-10.22,0.13],[0,0],[-10.87,0],[0,0],[-3.744,0],[-16.46,0],[0,-0.433],[0,0],[0,0],[0,5.273]],"o":[[14.75,-0.016],[3.969,0],[0,0],[7.75,0],[0,0],[10.17,0],[0,0],[2.89,0],[10.131,0],[0,0.104],[0,12.058],[0,0],[0,0],[0,-0.063]],"v":[[-93,-65],[-42.02,-65.028],[-31.423,-65.045],[-31,-65.037],[-0.52,-65.005],[0,-65.005],[30.62,-65.04],[31.485,-65.045],[41.994,-65.02],[93,-65],[148.75,-71.939],[139.5,91],[-147,86],[-155.672,-60.871]],"c":true}]},{"t":41}],"ix":2},"nm":"Path 1","mn":"ADBE Vector Shape - Group","hd":false},{"ty":"st","c":{"a":0,"k":[0.945097982883,0.945097982883,0.949020028114,1],"ix":3},"o":{"a":0,"k":100,"ix":4},"w":{"a":0,"k":1,"ix":5},"lc":1,"lj":1,"ml":4,"nm":"Stroke 1","mn":"ADBE Vector Graphic - Stroke","hd":false},{"ty":"fl","c":{"a":0,"k":[1,1,1,1],"ix":4},"o":{"a":0,"k":100,"ix":5},"r":1,"nm":"Fill 1","mn":"ADBE Vector Graphic - Fill","hd":false},{"ty":"tr","p":{"a":0,"k":[0,0],"ix":2},"a":{"a":0,"k":[0,0],"ix":1},"s":{"a":0,"k":[100,100],"ix":3},"r":{"a":0,"k":0,"ix":6},"o":{"a":0,"k":100,"ix":7},"sk":{"a":0,"k":0,"ix":4},"sa":{"a":0,"k":0,"ix":5},"nm":"Transform"}],"nm":"路径","np":3,"cix":2,"ix":1,"mn":"ADBE Vector Group","hd":false}],"ip":0,"op":42,"st":1,"bm":0}],"markers":[]}